qcloud_cos_v3/__init__.py
qcloud_cos_v3/cos_auth.py
qcloud_cos_v3/cos_client.py
qcloud_cos_v3/cos_config.py
qcloud_cos_v3/cos_cred.py
qcloud_cos_v3/cos_err.py
qcloud_cos_v3/cos_op.py
qcloud_cos_v3/cos_params_check.py
qcloud_cos_v3/cos_request.py
qcloud_cos_v3-0.1.0.dist-info/DESCRIPTION.rst
qcloud_cos_v3-0.1.0.dist-info/METADATA
qcloud_cos_v3-0.1.0.dist-info/RECORD
qcloud_cos_v3-0.1.0.dist-info/WHEEL
qcloud_cos_v3-0.1.0.dist-info/metadata.json
qcloud_cos_v3-0.1.0.dist-info/top_level.txt
