Metadata-Version: 2.0
Name: qcloud-cos-v3
Version: 0.1.0
Summary: python sdk for tencent qcloud cos
Home-page: UNKNOWN
Author: chengwu
Author-email: chengwu@tencent.com
License: MIT License
Platform: UNKNOWN
Requires-Dist: requests
